awtrix_light_client/__init__.py
awtrix_light_client/http_client.py
awtrix_light_client/http_settings.py
awtrix_light_client/models/__init__.py
awtrix_light_client/models/application.py
awtrix_light_client/models/effect.py
awtrix_light_client/models/loop.py
awtrix_light_client/models/moodlight.py
awtrix_light_client/models/screen.py
awtrix_light_client/models/setting.py
awtrix_light_client/models/stat.py
awtrix_light_client/models/transition.py
awtrix_light_client/models/utils.py
awtrix_light_client-2.0.0.dist-info/WHEEL
awtrix_light_client-2.0.0.dist-info/METADATA
awtrix_light_client-2.0.0.dist-info/RECORD
