Metadata-Version: 2.3
Name: awtrix-light-client
Version: 2.0.0
Summary: awtrix-light HTTP client to be used with Ulanzi clock
Keywords: awtrix-light,awtrix
Author: Ludovic Ortega
Author-email: Ludovic Ortega <ludovic.ortega@adminafk.fr>
Classifier: Programming Language :: Python
Classifier: Programming Language :: Python :: 3.10
Classifier: Programming Language :: Python :: 3.11
Classifier: Programming Language :: Python :: 3.12
Classifier: Programming Language :: Python :: 3.13
Classifier: Programming Language :: Python :: 3.14
Classifier: Operating System :: OS Independent
Classifier: License :: OSI Approved :: CEA CNRS Inria Logiciel Libre License, version 2.1 (CeCILL-2.1)
Classifier: Topic :: Utilities
Requires-Dist: httpx>=0.22.0,<1.0.0
Requires-Dist: pydantic>=2.12.5,<3.0.0
Requires-Dist: pydantic-settings>=2.12.0,<3.0.0
Requires-Dist: pydantic-extra-types>=2.11.0,<3.0.0
Requires-Python: >=3.10, <4.0.0
Project-URL: Homepage, https://github.com/M0NsTeRRR/awtrix-light-client
Project-URL: Repository, https://github.com/M0NsTeRRR/awtrix-light-client
Project-URL: Issues, https://github.com/M0NsTeRRR/awtrix-light-client/issues
Project-URL: Documentation, https://m0nsterrr.github.io/awtrix-light-client/latest/
Project-URL: Funding, https://ko-fi.com/ludovicortega
